private_assistant_commons/__init__.py
private_assistant_commons/base_skill.py
private_assistant_commons/database/__init__.py
private_assistant_commons/database/device_models.py
private_assistant_commons/database/intent_pattern_models.py
private_assistant_commons/database/postgres_config.py
private_assistant_commons/database/skill_models.py
private_assistant_commons/intent/__init__.py
private_assistant_commons/intent/models.py
private_assistant_commons/messages.py
private_assistant_commons/metrics.py
private_assistant_commons/mqtt_connection_handler.py
private_assistant_commons/py.typed
private_assistant_commons/skill_config.py
private_assistant_commons/skill_context.py
private_assistant_commons/skill_logger.py
private_assistant_commons-6.3.0.dist-info/licenses/LICENSE
private_assistant_commons-6.3.0.dist-info/WHEEL
private_assistant_commons-6.3.0.dist-info/METADATA
private_assistant_commons-6.3.0.dist-info/RECORD
