Metadata-Version: 2.4
Name: private-assistant-commons
Version: 6.3.0
Summary: Common utilities and base functionalities for all skills in the Private Assistant ecosystem.
Keywords: 
Author: stkr22
Author-email: stkr22 <stkr22@github.com>
License-Expression: GPL-3.0-only
License-File: LICENSE
Classifier: Development Status :: 4 - Beta
Classifier: Environment :: Console
Classifier: Programming Language :: Python
Classifier: Intended Audience :: Developers
Classifier: Operating System :: OS Independent
Classifier: Topic :: Home Automation
Classifier: Programming Language :: Python :: 3.12
Classifier: Programming Language :: Python :: 3.13
Requires-Dist: pydantic~=2.12.5
Requires-Dist: aiomqtt~=2.5.0
Requires-Dist: pyyaml~=6.0.1
Requires-Dist: rich~=14.2.0
Requires-Dist: pydantic-settings>=2.11.0
Requires-Dist: sqlmodel~=0.0.25
Requires-Dist: asyncpg~=0.31.0
Requires-Python: >=3.12, <3.14
Project-URL: Homepage, https://github.com/stkr22/private-assistant-commons-py
Project-URL: Repository, https://github.com/stkr22/private-assistant-commons-py
Project-URL: Documentation, https://github.com/stkr22/private-assistant-commons-py/tree/main/docs
Project-URL: Issues, https://github.com/stkr22/private-assistant-commons-py/issues
Project-URL: Changelog, https://github.com/stkr22/private-assistant-commons-py/blob/main/CHANGELOG.md
